execexam/__init__.py
execexam/advise.py
execexam/convert.py
execexam/debug.py
execexam/display.py
execexam/enumerations.py
execexam/exceptions.py
execexam/extract.py
execexam/main.py
execexam/pytest_plugin.py
execexam/util.py
execexam-0.3.3.dist-info/METADATA
execexam-0.3.3.dist-info/WHEEL
execexam-0.3.3.dist-info/entry_points.txt
execexam-0.3.3.dist-info/RECORD
