Metadata-Version: 2.1
Name: execexam
Version: 0.3.3
Summary: ExecExam runs executable examinations, providing feedback and assistance!
Author: Hemani Alaparthi
Author-email: alaparthi01@allegheny.edu
Requires-Python: >=3.11,<4.0
Classifier: Programming Language :: Python :: 3
Classifier: Programming Language :: Python :: 3.11
Classifier: Programming Language :: Python :: 3.12
Classifier: Programming Language :: Python :: 3.13
Requires-Dist: coverage (>=7.4.3,<8.0.0)
Requires-Dist: litellm[proxy] (>=1.43.15,<2.0.0)
Requires-Dist: openai (>=1.41.0,<2.0.0)
Requires-Dist: pytest (>=8.1.1,<9.0.0)
Requires-Dist: pytest-cov (>=4.1.0,<5.0.0)
Requires-Dist: pytest-json-report (>=1.5.0,<2.0.0)
Requires-Dist: rich (>=13.7.1,<14.0.0)
Requires-Dist: typer (>=0.12.3,<0.13.0)
Requires-Dist: validators (>=0.33.0,<0.34.0)
